resolved/__init__.py
resolved/domlabs.py
reSolved-0.0.3.dist-info/METADATA
reSolved-0.0.3.dist-info/WHEEL
reSolved-0.0.3.dist-info/top_level.txt
reSolved-0.0.3.dist-info/RECORD
