Metadata-Version: 2.1
Name: reSolved
Version: 0.0.3
Summary: reSolved is an upcoming captcha solving service, capable of solving reCaptcha, hCaptcha, GeeTest as fast as sub 5 seconds. reSolved is designed to handle heavy workloads, unlike other captcha solving services. We strive to improve the reSolved experience every single day - which is why we are releasing libraries that make an already simple integration process completely seamless.
Home-page: https://github.com/pypa/sampleproject
Author: mechaadi
Author-email: as808780@gmail.com
License: UNKNOWN
Platform: UNKNOWN
Classifier: Programming Language :: Python :: 3
Classifier: License :: OSI Approved :: MIT License
Classifier: Operating System :: OS Independent
Requires-Python: >=3.6
